biosimulators_test_suite/__init__.py
biosimulators_test_suite/_version.py
biosimulators_test_suite/config.py
biosimulators_test_suite/data_model.py
biosimulators_test_suite/exceptions.py
biosimulators_test_suite/exec_cli.py
biosimulators_test_suite/exec_core.py
biosimulators_test_suite/exec_gh_action.py
biosimulators_test_suite/results/__init__.py
biosimulators_test_suite/results/data_model.py
biosimulators_test_suite/results/io.py
biosimulators_test_suite/test_case/__init__.py
biosimulators_test_suite/test_case/cli.py
biosimulators_test_suite/test_case/combine_archive.py
biosimulators_test_suite/test_case/docker_image.py
biosimulators_test_suite/test_case/log.py
biosimulators_test_suite/test_case/published_project.py
biosimulators_test_suite/test_case/results_report.py
biosimulators_test_suite/test_case/sedml.py
biosimulators_test_suite/test_case/utils.py
biosimulators_test_suite/test_warnings.py
biosimulators_test_suite/utils.py
biosimulators_test_suite-0.2.dist-info/LICENSE
biosimulators_test_suite-0.2.dist-info/METADATA
biosimulators_test_suite-0.2.dist-info/WHEEL
biosimulators_test_suite-0.2.dist-info/entry_points.txt
biosimulators_test_suite-0.2.dist-info/RECORD
