Metadata-Version: 2.1
Name: biosimulators-test-suite
Version: 0.2
Summary: Tools for validating that biosimulation tools are consistent with the BioSimulators standards
Home-page: https://github.com/biosimulators/Biosimulators_test_suite
License: MIT License (MIT)
Keywords: systems,biology,modeling,simulation,BioSimulators
Author: Center for Reproducible Modeling
Author-email: info@biosimulators.org
Requires-Python: >=3.10,<3.11
Classifier: Development Status :: 3 - Alpha
Classifier: Intended Audience :: Science/Research
Classifier: License :: OSI Approved :: MIT License
Classifier: License :: Other/Proprietary License
Classifier: Programming Language :: Python :: 3
Classifier: Programming Language :: Python :: 3.10
Classifier: Topic :: Scientific/Engineering :: Bio-Informatics
Requires-Dist: biosimulators-utils[bngl,cellml,containers,escher,lems,logging,neuroml,sbml,simularium,smoldyn] (>=0.2)
Requires-Dist: cement (<=3.0.6)
Requires-Dist: docker (>=7.1.0,<8.0.0)
Requires-Dist: natsort (<=8.1.0)
Requires-Dist: pypdf2 (<=2.8.1)
Requires-Dist: python-dateutil (<2.9)
Requires-Dist: pyyaml (<5.4)
Requires-Dist: requests (<=2.28.1)
Requires-Dist: simplejson (<3.17.0)
Requires-Dist: termcolor (<1.2)
Project-URL: Repository, https://github.com/biosimulators/Biosimulators_test_suite
